brevo_analytics/__init__.py
brevo_analytics/admin.py
brevo_analytics/api_views.py
brevo_analytics/apps.py
brevo_analytics/i18n.py
brevo_analytics/models.py
brevo_analytics/serializers.py
brevo_analytics/tests.py
brevo_analytics/urls.py
brevo_analytics/webhooks.py
brevo_analytics/locale/it/LC_MESSAGES/django.mo
brevo_analytics/locale/it/LC_MESSAGES/django.po
brevo_analytics/management/__init__.py
brevo_analytics/management/commands/__init__.py
brevo_analytics/management/commands/clean_internal_emails.py
brevo_analytics/management/commands/import_brevo_logs.py
brevo_analytics/management/commands/manage_blacklist.py
brevo_analytics/management/commands/recalculate_stats.py
brevo_analytics/management/commands/verify_brevo_stats.py
brevo_analytics/management/commands/verify_senders.py
brevo_analytics/management/commands/archive/fix_naive_datetimes.py
brevo_analytics/management/commands/archive/import_brevo_csv.py
brevo_analytics/management/commands/archive/sync_brevo_sent_at.py
brevo_analytics/migrations/0001_initial.py
brevo_analytics/migrations/0002_alter_brevomessage_options_brevomessage_sent_at_and_more.py
brevo_analytics/migrations/0003_rename_email_brevoemail_and_unique_constraint.py
brevo_analytics/migrations/0004_alter_brevoemail_options_brevoemail_blacklist_info.py
brevo_analytics/migrations/0005_brevoemail_sender_email.py
brevo_analytics/migrations/__init__.py
brevo_analytics/static/brevo_analytics/css/admin-overrides.css
brevo_analytics/static/brevo_analytics/css/app.css
brevo_analytics/static/brevo_analytics/js/app.js
brevo_analytics/static/brevo_analytics/js/blacklist-app.js
brevo_analytics/static/brevo_analytics/js/i18n-helper.js
brevo_analytics/templates/admin/brevo_analytics/config_error.html
brevo_analytics/templates/admin/brevo_analytics/dashboard.html
brevo_analytics/templates/admin/brevo_analytics/email_detail.html
brevo_analytics/templates/admin/brevo_analytics/email_list.html
brevo_analytics/templates/brevo_analytics/blacklist_spa.html
django_brevo_analytics-0.2.5.dist-info/licenses/AUTHORS.md
django_brevo_analytics-0.2.5.dist-info/licenses/LICENSE
django_brevo_analytics-0.2.5.dist-info/METADATA
django_brevo_analytics-0.2.5.dist-info/WHEEL
django_brevo_analytics-0.2.5.dist-info/top_level.txt
django_brevo_analytics-0.2.5.dist-info/RECORD
