Metadata-Version: 2.4
Name: django-brevo-analytics
Version: 0.2.5
Summary: Django admin integration for Brevo transactional email analytics
Author-email: Guglielmo Celata <guglielmo.celata@gmail.com>
License: MIT
Project-URL: Homepage, https://github.com/guglielmo/django-brevo-analytics
Project-URL: Documentation, https://github.com/guglielmo/django-brevo-analytics/blob/main/README.md
Project-URL: Repository, https://github.com/guglielmo/django-brevo-analytics
Project-URL: Changelog, https://github.com/guglielmo/django-brevo-analytics/blob/main/CHANGELOG.md
Classifier: Environment :: Web Environment
Classifier: Framework :: Django
Classifier: Framework :: Django :: 4.2
Classifier: Intended Audience :: Developers
Classifier: License :: OSI Approved :: MIT License
Classifier: Operating System :: OS Independent
Classifier: Programming Language :: Python
Classifier: Programming Language :: Python :: 3
Classifier: Programming Language :: Python :: 3.8
Classifier: Programming Language :: Python :: 3.9
Classifier: Programming Language :: Python :: 3.10
Classifier: Programming Language :: Python :: 3.11
Classifier: Topic :: Internet :: WWW/HTTP
Classifier: Topic :: Internet :: WWW/HTTP :: Dynamic Content
Requires-Python: >=3.8
License-File: LICENSE
License-File: AUTHORS.md
Requires-Dist: Django<5.0,>=4.2
Requires-Dist: djangorestframework>=3.14.0
Requires-Dist: django-cors-headers>=4.3.0
Requires-Dist: requests>=2.31.0
Requires-Dist: duckdb>=0.10.0
Dynamic: license-file
